LICENSE
MANIFEST.in
README.md
setup.py
ascetic/__init__.py
ascetic/static/css/bootstrap.min.css
ascetic/static/css/font-awesome.min.css
ascetic/static/css/magnific-popup.css
ascetic/static/css/style.css
ascetic/static/fonts/FontAwesome.otf
ascetic/static/fonts/fontawesome-webfont.eot
ascetic/static/fonts/fontawesome-webfont.svg
ascetic/static/fonts/fontawesome-webfont.ttf
ascetic/static/fonts/fontawesome-webfont.woff
ascetic/static/fonts/fontawesome-webfont.woff2
ascetic/static/js/bootstrap.min.js
ascetic/static/js/jquery.magnific-popup.min.js
ascetic/static/js/jquery.min.js
ascetic/static/js/script.js
ascetic/templates/base.html
ascetic/templates/index.html
ascetic/templates/blog/blog_post_detail.html
ascetic/templates/blog/blog_post_list.html
ascetic/templates/generic/includes/comments.html
ascetic/templates/portfolio/portfolio_post_detail.html
ascetic/templates/portfolio/portfolio_post_list.html
mezzanine_theme_ascetic.egg-info/PKG-INFO
mezzanine_theme_ascetic.egg-info/SOURCES.txt
mezzanine_theme_ascetic.egg-info/dependency_links.txt
mezzanine_theme_ascetic.egg-info/top_level.txt