Metadata-Version: 1.0
Name: mezzanine-theme-ascetic
Version: 0.1
Summary: Minimalistic Bootstrap template for Django/Mezzanine
Home-page: https://github.com/izhukov1992/mezzanine-theme-ascetic
Author: Ilya Zhukov
Author-email: izhukov1992@gmail.com
License: BSD License
Platform: UNKNOWN
